LICENSE.txt
MANIFEST.in
README.rst
requirements.txt
setup.py
bin/virga-asserts
bin/virga-samples
virga/__init__.py
virga/asserts.py
virga/common.py
virga/samples.py
virga.egg-info/PKG-INFO
virga.egg-info/SOURCES.txt
virga.egg-info/dependency_links.txt
virga.egg-info/not-zip-safe
virga.egg-info/requires.txt
virga.egg-info/top_level.txt
virga/providers/__init__.py
virga/providers/abstract.py
virga/providers/aws/__init__.py
virga/providers/aws/provider.py
virga/providers/aws/virgaclient.py
virga/providers/aws/definitions/addresses.yaml
virga/providers/aws/definitions/amis.yaml
virga/providers/aws/definitions/autoscaling.yaml
virga/providers/aws/definitions/certificates.yaml
virga/providers/aws/definitions/cloudformation.yaml
virga/providers/aws/definitions/cloudtrail.yaml
virga/providers/aws/definitions/db_instances.yaml
virga/providers/aws/definitions/elb.yaml
virga/providers/aws/definitions/elbv2.yaml
virga/providers/aws/definitions/instances.yaml
virga/providers/aws/definitions/network_acls.yaml
virga/providers/aws/definitions/route_tables.yaml
virga/providers/aws/definitions/security_groups.yaml
virga/providers/aws/definitions/subnets.yaml
virga/providers/aws/definitions/vpc_peering.yaml
virga/providers/aws/definitions/vpcs.yaml