Metadata-Version: 1.1
Name: virga
Version: 0.0.25
Summary: Analysing your Cloud infrastructure before the rain falls to the ground
Home-page: http://github.com/gurdulu/virga
Author: Gurdulù
Author-email: macgurd@gmail.com
License: MIT
Keywords: qa testing cloud aws
Platform: UNKNOWN
Classifier: Development Status :: 2 - Pre-Alpha
Classifier: License :: OSI Approved :: MIT License
Classifier: Programming Language :: Python
Classifier: Programming Language :: Python :: 3.6
Classifier: Programming Language :: Python :: 3.7
Classifier: Topic :: Software Development :: Quality Assurance
Classifier: Topic :: Software Development :: Testing
